LICENSE
README.md
docs/contributing.md
docs/index.md
docs/installation.md
docs/license.md
docs/overview.md
docs/usage.md
docs/api/embeddings.md
docs/api/errors.md
docs/api/graph.md
docs/api/models.md
docs/api/postgres.md
docs/api/queries.md
docs/api/utils.md
pgraf/__init__.py
pgraf/embeddings.py
pgraf/errors.py
pgraf/graph.py
pgraf/models.py
pgraf/postgres.py
pgraf/queries.py
pgraf/utils.py
schema/pgraf.sql
pgraf/py.typed
pgraf-1.0.0a2.dist-info/METADATA
pgraf-1.0.0a2.dist-info/WHEEL
pgraf-1.0.0a2.dist-info/licenses/LICENSE
pgraf-1.0.0a2.dist-info/RECORD
