Metadata-Version: 2.4
Name: pgraf
Version: 1.0.0a2
Summary: pgraf turns Postgres into a lightning fast property graph engine for use in AI Agents
Project-URL: Homepage, https://github.com/gmr/pgraf
Project-URL: Documentation, https://gmr.github.io/pgraf/
Project-URL: Bug Tracker, https://github.com/gmr/pgraf/issues
Author-email: "Gavin M. Roy" <gavinr@aweber.com>
License-Expression: BSD-3-Clause
License-File: LICENSE
Classifier: Development Status :: 3 - Alpha
Classifier: License :: OSI Approved :: BSD License
Classifier: Programming Language :: PL/SQL
Classifier: Programming Language :: Python :: 3
Classifier: Programming Language :: Python :: 3.12
Classifier: Programming Language :: Python :: 3.13
Classifier: Programming Language :: SQL
Classifier: Topic :: Database
Classifier: Topic :: Scientific/Engineering :: Artificial Intelligence
Classifier: Topic :: Software Development :: Libraries
Classifier: Typing :: Typed
Requires-Python: >=3.12
Requires-Dist: asyncstdlib<4,>=3.13.1
Requires-Dist: openai<2,>=1.74.0
Requires-Dist: orjson<4,>=3.10
Requires-Dist: pgvector<5,>=0.4.1
Requires-Dist: psycopg[pool]<4,>=3.2.4
Requires-Dist: pydantic<3,>=2.11.3
Requires-Dist: sentence-transformers<5,>=4.1.0
Requires-Dist: uuid-utils<0.11.0,>=0.10.0
Provides-Extra: dev
Requires-Dist: build<2,>=1; extra == 'dev'
Requires-Dist: mypy<2,>=1.7; extra == 'dev'
Requires-Dist: pre-commit<6,>=4; extra == 'dev'
Requires-Dist: pytest-cov; extra == 'dev'
Requires-Dist: pytest<9,>=8; extra == 'dev'
Requires-Dist: pyyaml; extra == 'dev'
Requires-Dist: ruff<1,>=0.8; extra == 'dev'
Provides-Extra: docs
Requires-Dist: black; extra == 'docs'
Requires-Dist: mkdocs-material<10,>9.5; extra == 'docs'
Requires-Dist: mkdocs<2,>=1.5; extra == 'docs'
Requires-Dist: mkdocstrings-python-xref<2,>=1.6; extra == 'docs'
Requires-Dist: mkdocstrings[python]<0.27,>=0.26; extra == 'docs'
